faninsar/__init__.py
faninsar/NSBAS/__init__.py
faninsar/NSBAS/freeze_thaw_process.py
faninsar/NSBAS/inversion.py
faninsar/NSBAS/tsmodels.py
faninsar/_core/__init__.py
faninsar/_core/data.py
faninsar/_core/device.py
faninsar/_core/geo_tools.py
faninsar/_core/logger.py
faninsar/_core/maks.py
faninsar/_core/pair_tools.py
faninsar/_core/sar_tools.py
faninsar/cmaps/__init__.py
faninsar/cmaps/GMT/__init__.py
faninsar/cmaps/GMT/abyss/abyss.txt
faninsar/cmaps/GMT/bathy/bathy.txt
faninsar/cmaps/GMT/cool/cool.txt
faninsar/cmaps/GMT/copper/copper.txt
faninsar/cmaps/GMT/cubhelix/cubhelix.txt
faninsar/cmaps/GMT/cyclic/cyclic.txt
faninsar/cmaps/GMT/dem1/dem1.txt
faninsar/cmaps/GMT/dem2/dem2.txt
faninsar/cmaps/GMT/dem3/dem3.txt
faninsar/cmaps/GMT/dem4/dem4.txt
faninsar/cmaps/GMT/drywet/drywet.txt
faninsar/cmaps/GMT/earth/earth.txt
faninsar/cmaps/GMT/elevation/elevation.txt
faninsar/cmaps/GMT/etopo1/etopo1.txt
faninsar/cmaps/GMT/geo/geo.txt
faninsar/cmaps/GMT/globe/globe.txt
faninsar/cmaps/GMT/gray/gray.txt
faninsar/cmaps/GMT/haxby/haxby.txt
faninsar/cmaps/GMT/hot/hot.txt
faninsar/cmaps/GMT/inferno/inferno.txt
faninsar/cmaps/GMT/jet/jet.txt
faninsar/cmaps/GMT/magma/magma.txt
faninsar/cmaps/GMT/nighttime/nighttime.txt
faninsar/cmaps/GMT/no_green/no_green.txt
faninsar/cmaps/GMT/ocean/ocean.txt
faninsar/cmaps/GMT/plasma/plasma.txt
faninsar/cmaps/GMT/polar/polar.txt
faninsar/cmaps/GMT/rainbow/rainbow.txt
faninsar/cmaps/GMT/red2green/red2green.txt
faninsar/cmaps/GMT/relief/relief.txt
faninsar/cmaps/GMT/seafloor/seafloor.txt
faninsar/cmaps/GMT/sealand/sealand.txt
faninsar/cmaps/GMT/seis/seis.txt
faninsar/cmaps/GMT/split/split.txt
faninsar/cmaps/GMT/srtm/srtm.txt
faninsar/cmaps/GMT/terra/terra.txt
faninsar/cmaps/GMT/topo/topo.txt
faninsar/cmaps/GMT/turbo/turbo.txt
faninsar/cmaps/GMT/viridis/viridis.txt
faninsar/cmaps/GMT/world/world.txt
faninsar/cmaps/GMT/wysiwyg/wysiwyg.txt
faninsar/cmaps/SCM/__init__.py
faninsar/cmaps/SCM/acton/acton.txt
faninsar/cmaps/SCM/bam/bam.txt
FanInSAR-0.0.1.dist-info/LICENSE
FanInSAR-0.0.1.dist-info/METADATA
FanInSAR-0.0.1.dist-info/WHEEL
FanInSAR-0.0.1.dist-info/top_level.txt
FanInSAR-0.0.1.dist-info/RECORD
