Metadata-Version: 2.1
Name: FanInSAR
Version: 0.0.1
Summary: A fantastic InSAR processing library, in a more pythonic way, to accelerate your InSAR processing workflow.
Home-page: https://github.com/Fanchengyan/FanInSAR
Author: Fancy
Author-email: fanchy14@lzu.edu.cn
Classifier: Programming Language :: Python :: 3
Classifier: License :: OSI Approved :: MIT License
Classifier: Operating System :: OS Independent
Requires-Python: >=3.8
License-File: LICENSE
Requires-Dist: geopandas
Requires-Dist: pandas
Requires-Dist: numpy
Requires-Dist: torch
Requires-Dist: matplotlib
Requires-Dist: data-downloader
Requires-Dist: rasterio >=1.0.26
Requires-Dist: xarray
Requires-Dist: psutil
Requires-Dist: rioxarray
Requires-Dist: netcdf4
Requires-Dist: h5netcdf
Requires-Dist: tqdm
Requires-Dist: rtree
